{
	"$schema": "https://json-schema.org/draft/2020-12/schema",
	"$id": "schema/bedrock/server/block/1.21.120/components/redstone_producer.json",
	"type": "object",
	"title": "Redstone Producer Component",
	"description": "If added to a block, indicates that it produces a redstone signal.",
	"additionalProperties": false,
	"properties": {
		"connected_faces": {
			"type": "array",
			"description": "The list of faces that are considered connected to the circuit.",
			"items": {
				"type": "string",
				"enum": ["north", "east", "south", "west", "up", "down"]
			}
		},
		"power": {
			"type": "integer",
			"description": "The strength of the redstone signal produced by this block.",
			"minimum": 0,
			"maximum": 15
		},
		"strongly_powered_face": {
			"type": "string",
			"description": "The block touching this face will become strongly powered with the signal level strength of 'power'.",
			"enum": ["north", "east", "south", "west", "up", "down"]
		},
		"transform_relative": {
			"type": "boolean",
			"default": false,
			"description": "If true, the strongly_powered_face and connected_faces properties will be rotated according to the minecraft:transformation component."
		}
	}
}
