{
	"$schema": "https://json-schema.org/draft/2020-12/schema",
	"$id": "schema/vanilla/client/identifiers.json",
	"definitions": {
		"particle_identifier": {
			"anyOf": [
				{ "type": "string", "maxLength": 256 },
				{
					"enum": [
						"minecraft:arrow_spell_emitter",
						"minecraft:balloon_gas_particle",
						"minecraft:basic_bubble_particle",
						"minecraft:basic_bubble_particle_manual",
						"minecraft:basic_crit_particle",
						"minecraft:basic_flame_particle",
						"minecraft:basic_portal_particle",
						"minecraft:basic_smoke_particle",
						"minecraft:biome_tinted_leaves_particle",
						"minecraft:bleach",
						"minecraft:block_destruct",
						"minecraft:block_slide",
						"minecraft:blue_flame_particle",
						"minecraft:breaking_item_icon",
						"minecraft:breaking_item_terrain",
						"minecraft:breeze_ground_particle",
						"minecraft:breeze_wind_explosion_emitter",
						"minecraft:bubble_column_bubble",
						"minecraft:bubble_column_down_particle",
						"minecraft:bubble_column_up_particle",
						"minecraft:camera_shoot_explosion",
						"minecraft:campfire_smoke_particle",
						"minecraft:campfire_tall_smoke_particle",
						"minecraft:candle_flame_particle",
						"minecraft:cauldron_spell_emitter",
						"minecraft:cauldron_bubble_particle",
						"minecraft:cauldron_splash_particle",
						"minecraft:cherry_leaves_particle",
						"minecraft:colored_flame_particle",
						"minecraft:conduit_particle",
						"minecraft:conduit_absorb_particle",
						"minecraft:conduit_attack_emitter",
						"minecraft:creaking_crumble_body",
						"minecraft:creaking_crumble_head",
						"minecraft:creaking_heart_trail",
						"minecraft:critical_hit_emitter",
						"minecraft:crop_growth_emitter",
						"minecraft:crop_growth_area_emitter",
						"minecraft:dolphin_move_particle",
						"minecraft:dragon_breath_fire",
						"minecraft:dragon_breath_lingering",
						"minecraft:dragon_breath_trail",
						"minecraft:dragon_death_explosion_emitter",
						"minecraft:dragon_destroy_block",
						"minecraft:dragon_dying_explosion",
						"minecraft:stalactite_lava_drip_particle",
						"minecraft:stalactite_water_drip_particle",
						"minecraft:dust_plume",
						"minecraft:electric_spark_particle",
						"minecraft:enchanting_table_particle",
						"minecraft:endrod",
						"minecraft:end_chest",
						"minecraft:elephant_tooth_paste_vapor_particle",
						"minecraft:evocation_fang_particle",
						"minecraft:evoker_spell",
						"minecraft:cauldron_explosion_emitter",
						"minecraft:death_explosion_emitter",
						"minecraft:egg_destroy_emitter",
						"minecraft:eyeofender_death_explode_particle",
						"minecraft:misc_fire_vapor_particle",
						"minecraft:explosion_particle",
						"minecraft:explosion_manual",
						"minecraft:eyeblossom_close",
						"minecraft:eyeblossom_open",
						"minecraft:eye_of_ender_bubble_particle",
						"minecraft:falling_border_dust_particle",
						"minecraft:falling_dust",
						"minecraft:falling_dust_concrete_powder_particle",
						"minecraft:falling_dust_dragon_egg_particle",
						"minecraft:falling_dust_gravel_particle",
						"minecraft:falling_dust_red_sand_particle",
						"minecraft:falling_dust_sand_particle",
						"minecraft:falling_dust_scaffolding_particle",
						"minecraft:falling_dust_top_snow_particle",
						"minecraft:firefly_particle",
						"minecraft:fish_hook_particle",
						"minecraft:fish_pos_particle",
						"minecraft:glow_particle",
						"minecraft:green_flame_particle",
						"minecraft:guardian_attack_particle",
						"minecraft:guardian_water_move_particle",
						"minecraft:heart_particle",
						"minecraft:honey_drip_particle",
						"minecraft:huge_explosion_lab_misc_emitter",
						"minecraft:huge_explosion_emitter",
						"minecraft:ice_evaporation_emitter",
						"minecraft:infested_ambient",
						"minecraft:infested_emitter",
						"minecraft:ink_emitter",
						"minecraft:knockback_roar_particle",
						"minecraft:lab_table_heatblock_dust_particle",
						"minecraft:lab_table_misc_mystical_particle",
						"minecraft:large_explosion",
						"minecraft:lava_drip_particle",
						"minecraft:lava_particle",
						"minecraft:llama_spit_smoke",
						"minecraft:magic_critical_hit_emitter",
						"minecraft:magnesium_salts_emitter",
						"minecraft:mobflame_emitter",
						"minecraft:mobflame_single",
						"minecraft:mobspell_emitter",
						"minecraft:mobspell_ambient",
						"minecraft:mobspell_lingering",
						"minecraft:mob_block_spawn_emitter",
						"minecraft:mob_portal",
						"minecraft:mycelium_dust_particle",
						"minecraft:nautilus_bubbles_particle",
						"minecraft:nectar_drip_particle",
						"minecraft:note_particle",
						"minecraft:obsidian_glow_dust_particle",
						"minecraft:obsidian_tear_particle",
						"minecraft:ominous_spawning_particle",
						"minecraft:oozing_ambient",
						"minecraft:oozing_emitter",
						"minecraft:pale_oak_leaves_particle",
						"minecraft:pause_mob_growth",
						"minecraft:phantom_trail_particle",
						"minecraft:portal_directional",
						"minecraft:portal_east_west",
						"minecraft:portal_north_south",
						"minecraft:portal_reverse_particle",
						"minecraft:raid_omen_ambient",
						"minecraft:raid_omen_emitter",
						"minecraft:rain_splash_particle",
						"minecraft:redstone_ore_dust_particle",
						"minecraft:redstone_repeater_dust_particle",
						"minecraft:redstone_torch_dust_particle",
						"minecraft:redstone_wire_dust_particle",
						"minecraft:reset_mob_growth",
						"minecraft:rising_border_dust_particle",
						"minecraft:sculk_charge_particle",
						"minecraft:sculk_charge_pop_particle",
						"minecraft:sculk_sensor_redstone_particle",
						"minecraft:sculk_soul_particle",
						"minecraft:shriek_particle",
						"minecraft:shulker_bullet",
						"minecraft:silverfish_grief_emitter",
						"minecraft:small_flame_particle",
						"minecraft:small_soul_fire_flame",
						"minecraft:smash_ground_particle",
						"minecraft:smash_ground_particle_center",
						"minecraft:sneeze",
						"minecraft:snowflake_particle",
						"minecraft:sonic_explosion",
						"minecraft:soul_particle",
						"minecraft:sparkler_emitter",
						"minecraft:splash_spell_emitter",
						"minecraft:sponge_absorb_water_particle",
						"minecraft:spore_blossom_ambient_particle",
						"minecraft:spore_blossom_shower_particle",
						"minecraft:squid_flee_particle",
						"minecraft:squid_ink_bubble",
						"minecraft:squid_move_particle",
						"minecraft:stunned_emitter",
						"minecraft:totem_particle",
						"minecraft:totem_manual",
						"minecraft:trial_omen_ambient",
						"minecraft:trial_omen_emitter",
						"minecraft:trial_omen_single",
						"minecraft:trial_spawner_detection",
						"minecraft:trial_spawner_detection_ominous",
						"minecraft:underwater_torch_particle",
						"minecraft:vault_connection_particle",
						"minecraft:vibration_signal",
						"minecraft:villager_angry",
						"minecraft:villager_happy",
						"minecraft:warden_dig",
						"minecraft:water_drip_particle",
						"minecraft:water_evaporation_actor_emitter",
						"minecraft:water_evaporation_bucket_emitter",
						"minecraft:water_evaporation_manual",
						"minecraft:water_splash_particle",
						"minecraft:water_splash_particle_manual",
						"minecraft:water_wake_particle",
						"minecraft:wax_particle",
						"minecraft:weaving_ambient",
						"minecraft:weaving_emitter",
						"minecraft:white_smoke_particle",
						"minecraft:wind_charged_ambient",
						"minecraft:wind_charged_emitter",
						"minecraft:wind_explosion_emitter",
						"minecraft:witchspell_emitter",
						"minecraft:wither_boss_invulnerable"
					]
				}
			]
		},
		"sound_event_identifier": {
			"enum": [
				"ambient.basalt_deltas.additions",
				"ambient.basalt_deltas.loop",
				"ambient.basalt_deltas.mood",
				"ambient.candle",
				"ambient.cave",
				"ambient.crimson_forest.additions",
				"ambient.crimson_forest.loop",
				"ambient.crimson_forest.mood",
				"ambient.nether_wastes.additions",
				"ambient.nether_wastes.loop",
				"ambient.nether_wastes.mood",
				"ambient.soulsand_valley.additions",
				"ambient.soulsand_valley.loop",
				"ambient.soulsand_valley.mood",
				"ambient.underwater.enter",
				"ambient.underwater.exit",
				"ambient.warped_forest.additions",
				"ambient.warped_forest.loop",
				"ambient.warped_forest.mood",
				"ambient.weather.the_end_light_flash",
				"apply_effect.bad_omen",
				"apply_effect.raid_omen",
				"apply_effect.trial_omen",
				"armor.break_wolf",
				"armor.crack_wolf",
				"armor.equip_chain",
				"armor.equip_copper",
				"armor.equip_diamond",
				"armor.equip_elytra",
				"armor.equip_generic",
				"armor.equip_gold",
				"armor.equip_iron",
				"armor.equip_leather",
				"armor.equip_netherite",
				"armor.equip_wolf",
				"armor.repair_wolf",
				"armor.unequip_wolf",
				"attach",
				"beacon.activate",
				"beacon.ambient",
				"beacon.deactivate",
				"beacon.power",
				"blast",
				"block.bamboo_sapling.place",
				"block.barrel.close",
				"block.barrel.open",
				"block.beehive.drip",
				"block.beehive.enter",
				"block.beehive.exit",
				"block.beehive.shear",
				"block.beehive.work",
				"block.bell.hit",
				"block.blastfurnace.fire_crackle",
				"block.campfire.crackle",
				"block.cartography_table.use",
				"block.click",
				"block.click.fail",
				"block.composter.empty",
				"block.composter.fill",
				"block.composter.fill_success",
				"block.composter.ready",
				"block.copper_bulb.turn_off",
				"block.copper_bulb.turn_on",
				"block.creaking_heart.trail",
				"block.decorated_pot.insert",
				"block.decorated_pot.insert_fail",
				"block.enchanting_table.use",
				"block.end_portal.spawn",
				"block.end_portal_frame.fill",
				"block.fletching_table.use",
				"block.frog_spawn.break",
				"block.frog_spawn.hatch",
				"block.furnace.lit",
				"block.grindstone.use",
				"block.loom.use",
				"block.scaffolding.climb",
				"block.sculk.spread",
				"block.sculk_catalyst.bloom",
				"block.sculk_sensor.place",
				"block.sculk_shrieker.place",
				"block.sculk_shrieker.shriek",
				"block.sign.waxed_interact_fail",
				"block.smithing_table.use",
				"block.smoker.smoke",
				"block.sniffer_egg.crack",
				"block.sniffer_egg.hatch",
				"block.stonecutter.use",
				"block.sweet_berry_bush.hurt",
				"block.sweet_berry_bush.pick",
				"block.turtle_egg.attack",
				"block.turtle_egg.break",
				"block.turtle_egg.crack",
				"block.turtle_egg.hatch",
				"bottle.dragonbreath",
				"bottle.empty",
				"bottle.fill",
				"bow",
				"bow.hit",
				"break",
				"breeze_wind_charge.burst",
				"bubble.down",
				"bubble.downinside",
				"bubble.pop",
				"bubble.up",
				"bubble.upinside",
				"bucket.empty.fish",
				"bucket.empty.lava",
				"bucket.empty.powder_snow",
				"bucket.empty.water",
				"bucket.fill.fish",
				"bucket.fill.lava",
				"bucket.fill.powder_snow",
				"bucket.fill.water",
				"bullet.hit",
				"bundle.drop_contents",
				"bundle.insert",
				"bundle.insert_fail",
				"bundle.remove_one",
				"burp",
				"cake.add_candle",
				"camera.take_picture",
				"cauldron_drip.lava.pointed_dripstone",
				"cauldron_drip.water.pointed_dripstone",
				"charge.sculk",
				"chest.closed",
				"chest.open",
				"chime.amethyst_block",
				"chorusdeath",
				"chorusgrow",
				"conduit.activate",
				"conduit.ambient",
				"conduit.attack",
				"conduit.deactivate",
				"conduit.short",
				"convert_mooshroom",
				"convert_to_drowned",
				"convert_to_frog",
				"convert_to_stray",
				"converted_to_zombified",
				"copper.wax.off",
				"copper.wax.on",
				"crafter.craft",
				"crafter.disable_slot",
				"crafter.fail",
				"crossbow.loading.end",
				"crossbow.loading.middle",
				"crossbow.loading.start",
				"crossbow.quick_charge.end",
				"crossbow.quick_charge.middle",
				"crossbow.quick_charge.start",
				"crossbow.shoot",
				"dash_ready",
				"deny",
				"detach",
				"drip.lava.pointed_dripstone",
				"drip.water.pointed_dripstone",
				"drop.slot",
				"enderchest.closed",
				"enderchest.open",
				"explode",
				"extinguish.candle",
				"extinguish.fire",
				"fire",
				"fizz",
				"glass",
				"glow_squid.ink_squirt",
				"horn_break",
				"horn_call0",
				"horn_call1",
				"horn_call2",
				"horn_call3",
				"horn_call4",
				"horn_call5",
				"horn_call6",
				"horn_call7",
				"ignite",
				"item.book.put",
				"item.copper_spear.attack_hit",
				"item.copper_spear.attack_miss",
				"item.copper_spear.use",
				"item.diamond_spear.attack_hit",
				"item.diamond_spear.attack_miss",
				"item.diamond_spear.use",
				"item.enchant.lunge1",
				"item.enchant.lunge2",
				"item.enchant.lunge3",
				"item.golden_spear.attack_hit",
				"item.golden_spear.attack_miss",
				"item.golden_spear.use",
				"item.iron_spear.attack_hit",
				"item.iron_spear.attack_miss",
				"item.iron_spear.use",
				"item.netherite_spear.attack_hit",
				"item.netherite_spear.attack_miss",
				"item.netherite_spear.use",
				"item.shield.block",
				"item.spear.attack_hit",
				"item.spear.attack_miss",
				"item.spear.use",
				"item.spyglass.stop_using",
				"item.spyglass.use",
				"item.stone_spear.attack_hit",
				"item.stone_spear.attack_miss",
				"item.stone_spear.use",
				"item.trident.hit",
				"item.trident.hit_ground",
				"item.trident.return",
				"item.trident.riptide_1",
				"item.trident.riptide_2",
				"item.trident.riptide_3",
				"item.trident.throw",
				"item.trident.thunder",
				"item.wooden_spear.attack_hit",
				"item.wooden_spear.attack_miss",
				"item.wooden_spear.use",
				"item_given",
				"item_taken",
				"item_thrown",
				"jump_to_block",
				"large.blast",
				"launch",
				"lava",
				"lava.pop",
				"lay_egg",
				"lay_spawn",
				"lead.break",
				"lead.leash",
				"lead.unleash",
				"leashknot.break",
				"leashknot.place",
				"levelup",
				"lodestone_compass.link_compass_to_lodestone",
				"mace.heavy_smash_ground",
				"mace.smash_air",
				"mace.smash_ground",
				"milk",
				"milk.screamer",
				"milk_suspiciously",
				"mob.armadillo.brush",
				"mob.armadillo.scute_drop",
				"mob.armor_stand.place",
				"mob.hoglin.converted_to_zombified",
				"mob.husk.convert_to_zombie",
				"mob.pig.death",
				"mob.player.hurt_drown",
				"mob.player.hurt_freeze",
				"mob.player.hurt_on_fire",
				"nearby_close",
				"nearby_closer",
				"nearby_closest",
				"note",
				"note.bass",
				"ominous_bottle.end_use",
				"ominous_item_spawner.about_to_spawn_item",
				"ominous_item_spawner.spawn_item",
				"ominous_item_spawner.spawn_item_begin",
				"particle.soul_escape.loud",
				"particle.soul_escape.quiet",
				"pause_growth",
				"pick_berries.cave_vines",
				"piston.in",
				"piston.out",
				"pop",
				"portal",
				"portal.travel",
				"potion.brewed",
				"power.off",
				"power.off.sculk_sensor",
				"power.on",
				"power.on.sculk_sensor",
				"pre_ram",
				"pre_ram.screamer",
				"pressure_plate.click_off",
				"pressure_plate.click_on",
				"pumpkin.carve",
				"raid.horn",
				"ram_impact",
				"ram_impact.screamer",
				"random.anvil_use",
				"record.11",
				"record.13",
				"record.5",
				"record.blocks",
				"record.cat",
				"record.chirp",
				"record.creator",
				"record.creator_music_box",
				"record.far",
				"record.lava_chicken",
				"record.mall",
				"record.mellohi",
				"record.otherside",
				"record.pigstep",
				"record.precipice",
				"record.relic",
				"record.stal",
				"record.strad",
				"record.tears",
				"record.wait",
				"record.ward",
				"remedy",
				"reset_growth",
				"respawn_anchor.ambient",
				"respawn_anchor.charge",
				"respawn_anchor.deplete",
				"respawn_anchor.set_spawn",
				"saddle",
				"scrape",
				"shear",
				"shulkerbox.closed",
				"shulkerbox.open",
				"smithing_table.use",
				"sonic_boom",
				"sonic_charge",
				"splash",
				"sponge.absorb",
				"squid.ink_squirt",
				"teleport",
				"thorns",
				"tilt_down.big_dripleaf",
				"tilt_up.big_dripleaf",
				"tongue",
				"trial_spawner.ambient",
				"trial_spawner.ambient_ominous",
				"trial_spawner.charge_activate",
				"trial_spawner.close_shutter",
				"trial_spawner.detect_player",
				"trial_spawner.eject_item",
				"trial_spawner.open_shutter",
				"trial_spawner.spawn_mob",
				"tripod",
				"twinkle",
				"ui.cartography_table.take_result",
				"ui.loom.take_result",
				"ui.stonecutter.take_result",
				"unfect",
				"vault.activate",
				"vault.ambient",
				"vault.close_shutter",
				"vault.deactivate",
				"vault.eject_item",
				"vault.insert_item",
				"vault.insert_item_fail",
				"vault.open_shutter",
				"vault.reject_rewarded_player",
				"water",
				"wind_charge.burst",
				"ambient.basalt_deltas.additions",
				"ambient.basalt_deltas.loop",
				"ambient.basalt_deltas.mood",
				"ambient.cave",
				"ambient.crimson_forest.additions",
				"ambient.crimson_forest.loop",
				"ambient.crimson_forest.mood",
				"ambient.nether_wastes.additions",
				"ambient.nether_wastes.loop",
				"ambient.nether_wastes.mood",
				"ambient.soulsand_valley.additions",
				"ambient.soulsand_valley.loop",
				"ambient.soulsand_valley.mood",
				"ambient.underwater.additions",
				"ambient.underwater.loop",
				"ambient.warped_forest.additions",
				"ambient.warped_forest.loop",
				"ambient.warped_forest.mood",
				"amethyst_block",
				"amethyst_cluster",
				"ancient_debris",
				"anvil",
				"azalea",
				"azalea_leaves",
				"bamboo",
				"bamboo_wood",
				"bamboo_wood_hanging_sign",
				"basalt",
				"big_dripleaf",
				"bone_block",
				"calcite",
				"candle",
				"cave_vines",
				"chain",
				"cherry_leaves",
				"cherry_wood",
				"cherry_wood_hanging_sign",
				"chiseled_bookshelf",
				"cloth",
				"copper",
				"copper_bulb",
				"copper_chest",
				"copper_chest_oxidized",
				"copper_chest_weathered",
				"copper_golem_statue",
				"copper_grate",
				"coral",
				"creaking_heart",
				"decorated_pot",
				"deepslate",
				"deepslate_bricks",
				"dirt_with_roots",
				"dried_ghast",
				"dripstone_block",
				"frog_spawn",
				"froglight",
				"fungus",
				"glass",
				"glow_lichen",
				"grass",
				"gravel",
				"hanging_roots",
				"hanging_sign",
				"heavy_core",
				"honey_block",
				"iron",
				"ladder",
				"lantern",
				"large_amethyst_bud",
				"leaf_litter",
				"lodestone",
				"mangrove_roots",
				"medium_amethyst_bud",
				"metal",
				"mob_spawner",
				"moss_block",
				"moss_carpet",
				"mud",
				"mud_bricks",
				"muddy_mangrove_roots",
				"nether_brick",
				"nether_gold_ore",
				"nether_sprouts",
				"nether_wart",
				"nether_wood",
				"nether_wood_hanging_sign",
				"netherite",
				"netherrack",
				"normal",
				"nylium",
				"packed_mud",
				"pink_petals",
				"pointed_dripstone",
				"polished_tuff",
				"powder_snow",
				"resin",
				"resin_brick",
				"roots",
				"sand",
				"scaffolding",
				"sculk",
				"sculk_catalyst",
				"sculk_sensor",
				"sculk_shrieker",
				"sculk_vein",
				"shelf",
				"shroomlight",
				"slime",
				"small_amethyst_bud",
				"snow",
				"soul_sand",
				"soul_soil",
				"sponge",
				"spore_blossom",
				"stem",
				"stone",
				"suspicious_gravel",
				"suspicious_sand",
				"trial_spawner",
				"tuff",
				"tuff_bricks",
				"turtle_egg",
				"vault",
				"vines",
				"web",
				"weeping_vines",
				"wet_sponge",
				"wood"
			]
		}
	}
}
